{"url": "https://www.geektime.co.il/geekjob300816/", "type": "article", "title": "10 \u05de\u05e9\u05e8\u05d5\u05ea \u05d7\u05de\u05d5\u05ea \u05dc\u05de\u05e4\u05ea\u05d7\u05d9 \u05de\u05d5\u05d1\u05d9\u05d9\u05dc", "description": "\u05e8\u05d9\u05db\u05d6\u05e0\u05d5 \u05e2\u05d1\u05d5\u05e8\u05db\u05dd 10 \u05de\u05e9\u05e8\u05d5\u05ea \u05d8\u05e8\u05d9\u05d5\u05ea \u05de\u05d4\u05dc\u05d5\u05d7\u05d5\u05ea \u05e9\u05dc\u05e0\u05d5 \u05e2\u05dd \u05db\u05dc \u05d4\u05e4\u05e8\u05d8\u05d9\u05dd \u05d4\u05e8\u05dc\u05d5\u05d5\u05e0\u05d8\u05d9\u05dd. \u05e2\u05db\u05e9\u05d9\u05d5 \u05e0\u05d5\u05ea\u05e8 \u05dc\u05db\u05dd \u05e8\u05e7 \u05dc\u05e2\u05d1\u05d5\u05e8, \u05dc\u05d1\u05d3\u05d5\u05e7 \u05d5\u05dc\u05e4\u05e0\u05d5\u05ea \u05dc\u05d0\u05dc\u05d5 \u05d4\u05e8\u05dc\u05d5\u05d5\u05e0\u05d8\u05d9\u05dd \u05e2\u05d1\u05d5\u05e8\u05db\u05dd", "image": "https://files.geektime.co.il/wp-content/uploads/2016/08/GettyImages-453854350.jpg", "tag": "\u05d0\u05d9\u05e0\u05d8\u05e8\u05e0\u05d8", "publisher": "https://www.facebook.com/geektimecoil", "published_time": "2016-09-01T13:20:10Z", "modified_time": "2016-09-01T12:19:29Z", "articleBody": "\u05e8\u05d9\u05db\u05d6\u05e0\u05d5 \u05e2\u05d1\u05d5\u05e8\u05db\u05dd 10 \u05de\u05e9\u05e8\u05d5\u05ea \u05d8\u05e8\u05d9\u05d5\u05ea \u05de\u05d4\u05dc\u05d5\u05d7\u05d5\u05ea \u05e9\u05dc\u05e0\u05d5 \u05e2\u05dd \u05db\u05dc \u05d4\u05e4\u05e8\u05d8\u05d9\u05dd \u05d4\u05e8\u05dc\u05d5\u05d5\u05e0\u05d8\u05d9\u05dd. \u05e2\u05db\u05e9\u05d9\u05d5 \u05e0\u05d5\u05ea\u05e8 \u05dc\u05db\u05dd \u05e8\u05e7 \u05dc\u05e2\u05d1\u05d5\u05e8, \u05dc\u05d1\u05d3\u05d5\u05e7 \u05d5\u05dc\u05e4\u05e0\u05d5\u05ea \u05dc\u05d0\u05dc\u05d5 \u05d4\u05e8\u05dc\u05d5\u05d5\u05e0\u05d8\u05d9\u05dd \u05e2\u05d1\u05d5\u05e8\u05db\u05dd\n\n\u05e7\u05e8\u05d3\u05d9\u05d8 \u05ea\u05de\u05d5\u05e0\u05d4: Getty Images Israel\n\u05d0\u05d7\u05ea \u05d4\u05de\u05d8\u05e8\u05d5\u05ea \u05dc\u05e9\u05de\u05df \u05d9\u05d9\u05e1\u05d3\u05e0\u05d5 \u05d0\u05ea \u05d2\u05d9\u05e7\u05d8\u05d9\u05d9\u05dd \u05d4\u05d9\u05ea\u05d4 \u05dc\u05e7\u05d3\u05dd \u05d0\u05ea \u05e7\u05d4\u05d9\u05dc\u05ea \u05d4\u05d4\u05d9\u05d9\u05d8\u05e7 \u05d1\u05d0\u05e8\u05e5. \u05d1\u05e4\u05d5\u05e1\u05d8 \u05d4\u05d2\u05d9\u05e7\u05d2\u2019\u05d5\u05d1 \u05d4\u05e9\u05d1\u05d5\u05e2\u05d9, \u05d0\u05e0\u05d7\u05e0\u05d5 \u05de\u05e4\u05e8\u05e1\u05de\u05d9\u05dd \u05d7\u05dc\u05e7 \u05de\u05d4\u05de\u05e9\u05e8\u05d5\u05ea \u05d4\u05de\u05e4\u05d5\u05e8\u05e1\u05de\u05d5\u05ea \u05d1\u05dc\u05d5\u05d7 \u05de\u05e9\u05e8\u05d5\u05ea \u05d4\u05d4\u05d9\u05d9\u05d8\u05e7 \u05d4\u05d7\u05d3\u05e9 \u05e9\u05dc \u05d2\u05d9\u05e7\u05d8\u05d9\u05d9\u05dd. \u05d0\u05dd \u05d0\u05ea\u05dd \u05de\u05e2\u05d5\u05e0\u05d9\u05d9\u05e0\u05d9\u05dd \u05dc\u05de\u05e6\u05d5\u05d0 \u05de\u05e9\u05e8\u05d5\u05ea \u05e0\u05d5\u05e1\u05e4\u05d5\u05ea \u05d0\u05d5 \u05dc\u05e4\u05e8\u05e1\u05dd \u05de\u05e9\u05e8\u05d5\u05ea \u05e9\u05dc\u05db\u05dd, \u05d0\u05ea\u05dd \u05de\u05d5\u05d6\u05de\u05e0\u05d9\u05dd \u05dc\u05e2\u05e9\u05d5\u05ea \u05d6\u05d0\u05ea \u05d1\u05d0\u05de\u05e6\u05e2\u05d5\u05ea \u05dc\u05d5\u05d7 \u05d4\u05de\u05e9\u05e8\u05d5\u05ea \u05d4\u05d7\u05d3\u05e9 \u05e9\u05dc\u05e0\u05d5 \u2013 Geeklist. \u05e9\u05ea\u05e4\u05d5 \u05d0\u05ea \u05d4\u05e4\u05d5\u05e1\u05d8 \u05d5\u05d4\u05e2\u05d1\u05d9\u05e8\u05d5 \u05d4\u05dc\u05d0\u05d4 \u05db\u05d3\u05d9 \u05dc\u05e2\u05d6\u05d5\u05e8 \u05dc\u05d7\u05d1\u05e8\u05d5\u05ea \u05dc\u05d4\u05e4\u05d9\u05e5 \u05d0\u05ea \u05d4\u05de\u05e9\u05e8\u05d5\u05ea \u05d5\u05dc\u05d2\u05d5\u05dc\u05e9\u05d9 \u05d2\u05d9\u05e7\u05d8\u05d9\u05d9\u05dd \u05dc\u05de\u05e6\u05d5\u05d0 \u05d0\u05ea \u05d4\u05e2\u05d1\u05d5\u05d3\u05d4 \u05d4\u05d7\u05d3\u05e9\u05d4 \u05e9\u05d4\u05dd \u05de\u05d7\u05e4\u05e9\u05d9\u05dd.\nThe Web Developer will be will be part of OnStar Europe R&D and will be responsible for:\n\u2013 Mobile Web application development using current web technologies.\n\u2013 Vehicle Infotainment.\n\u2013 Design, implement and unit-test web software modules.\nRequirements:\n\u2013 Experience with Mobile web UI development.\n\u2013 Experience with Native Mobile Development iOS or Android.\n\u2013 Past experience in server and client software development.\n\u2013 Experience with current web technologies (Node.JS, TypeScript, HTML5, JavaScript, CSS, Sencha).\n\u2013 User and customer centric approach.\n\u2013 Hands on character.\n\u2013 Experience with global large scale production releases with multiple development.\n\u2013 Excellent communication skills \u2013 Fluent English.\n\u2013 Excellent organization, interpersonal and communication skills.\n\u2013 Ability to handle multiple assignments and tasks independently.\n\u2013 Bachelor\u2019s degree in in Computer science or related technical field or equivalent practical experience.\nTo send a CV for the position of Mobile Web Developer\u00a0\u2013 General Motors \u2013 \u05d2\u2019\u05e0\u05e8\u05dc \u05de\u05d5\u05d8\u05d5\u05e8\u05e1\n\u2013 Lead the technical and strategy, research, design, and implementation of cutting-edge technologies to influence industry-leading middleware, cloud, and mobile offerings.\nRequirements:\n\u2013 MS or PhD with 3+ years related industry experience.\n\u2013 Proven technical leadership.\n\u2013 Innovative and strategic thinking, research and self-learning skills.\n\u2013 Excellent interpersonal skills.\n\u2013 Business development and/or product management skills.\n\u2013 Good understanding of systems programming including distributed systems, multithreading, networking, performance analysis, etc.\n\u2013 Demonstrated proficiency and programming experience in C, C++ or Java, Knowledge of OOP.\n\u2013 Open source contribution is an advantage.\nTo send a CV for the position of Technical Leader/Manager in the Cloud and Mobile Dep.\u00a0\u2013 IBM\n\u2013 Design and lead complex features in our mobile SDK and mobile apps.\n\u2013 Work closely with the server team to design, build, test and release our mobile experience for users.\n\u2013 Offer the in depth knowledge of the Android platform that\u2019s required by our product team.\n\u2013 Create documentation for developers detailing the integration process and unique abilities you have helped create.\nRequirements:\n\u2013 Degree in Computer Science or equivalent.\n\u2013 Personal interest and passion for mobile development.\n\u2013 At least 5 years of software development experience.\n\u2013 At least 2 years of experience with native development for Android.\n\u2013 Proven experience delivering finished mobile applications.\n\u2013 Intermediate to advanced familiarity with GitHub.\n\u2013 Good communication and interpersonal skills.\n\u2013 Quick learner and self-managed.\n\u2013 Fluent English.\nTo send a CV for the position of Senior Android Developer\u00a0\u2013 LivePerson\nWe are looking for an iOS Developer who possesses a passion for pushing mobile technologies to the limits and will work with our team of talented engineers to design and build the next generation of our mobile application.\nRequirements:\n\u2013 Working experience in iOS development.\n\u2013 Proven working experience in software development.\n\u2013 Have published one or more iOS apps in the app store.\n\u2013 A deep familiarity with Objective-C and Cocoa Touch.\n\u2013 Experience working with iOS frameworks such as Core Data, Core Animation, Core Graphics and Core Text.\n\u2013 Experience with third-party libraries and APIs.\n\u2013 Working knowledge of the general mobile landscape, architectures, trends, and emerging technologies.\n\u2013 Solid understanding of the full mobile development life cycle.\n\u2013 BS/MS degree in Computer Science, Engineering or a related subject.\nTo send a CV for the position of iOS Developer\u00a0\u2013 AGT International\n\u2013 Work with other members of the engineering team on architecture, design and development.\n\u2013 Provide design leadership and technical assistance to other team members\n\u2013 Must communicate effectively with management and peers.\n\u2013 Must be self-motivated, have a strong team orientation, learn quickly and possess excellent communication and interpersonal skill.\n\u2013 Passionate about mobile design and development.\nRequirements:\n\u2013 2+ years implementing with Objective-C as a primary language.\n\u2013 Experience with iOS and Cocoa Frameworks.\n\u2013 Common design patterns and idioms as they relate to Objective-C and Cocoa.\n\u2013 XCode environment (Interface Builder, GDB, Instruments, etc).\n\u2013 ARC and memory management.\n\u2013 Solid understanding of computer fundamentals.\n\u2013 Working knowledge of agile development processes.\n\u2013 Proud to deliver well-tested quality code with each release.\nTo send a CV for the position of IOS Developer\u00a0\u2013 JIVE\n\u2013 A chance to participate in the creation of exciting projects \u2013 our games are played by millions!\n\u2013 An amazing team of young, capable, like-minded peers and a \u201cwork hard, play hard\u201d attitude.\n\u2013 A chance to secure your own pot of gold (figuratively speaking, and pending the results of your interview). Be aware that there is ALMOST zero chance of being given either a pot of gold, or a Leprechaun.\n\u2013 A chance to take your professional career to the next level.\n\u2013 A great opportunity for growth and professional development.\n\u2013 Conferences, training and seminars to improve your skills.\n\u2013 A super cool office in a convenient location with parking lot.\n\u2013 Employment and social benefits in accordance with local legislation.\nRequirements:\n\u2013 Strong C++ skills and the ability to code and architect various core engine systems.\n\u2013 A keen analytical mind, with strong problem solving skills.\n\u2013 Firm grasp of 3D math, including transforms and quaternions.\n\u2013 Experience with multiple core system tasks, such as graphics, tools, video, audio, networking, memory handling, script compilers, threading.\n\u2013 OpenGL rendering experience.\n\u2013 Performance optimization skills.\n\u2013 At least 3 years of professional experience.\n\u2013 Strong Objective-C and Java skills experience.\n\u2013 Well versed in games and the ability to articulate what is strong/weak about the design of existing games.\nTo send a CV for the position of C++ Mobile Developer\u00a0\u2013 Plarium\nWe\u2019re looking for an experienced, professional, and highly motivated Android Engineers to join our cutting-edge Android team developing the next AT&T over-the-top Netflix competitor!\nThink about a TV, not an app, while support any Android device, including: Smartphones, Tablets, Android TV, Wearables & Amazon Fire TV, to bring TV everywhere!\nIt\u2019s going to turn some heads in the industry\u2026\nRequirements:\n\u2013 Solid experience with Java and the Android SDK.\n\u2013 Experience building rich Android UI application for different devices.\n\u2013 Strong problem-solving and critical-thinking skills.\n\u2013 Leading agenda based on practice engineering & Clean Architecture.\n\u2013 Experience building applications that talk to RESTful web services.\n\u2013 Experience writing multi-threaded, asynchronous code.\n\u2013 Understanding of software design patterns and architectural principles.\n\u2013 Attention to quality through unit tests, automation scripts, and code reviews.\n\u2013 Experience with Android internals.\n\u2013 Strong computer science fundamentals gained through Bachelor\u2019s degree in CS, Software Engineering or equivalent.\nTo send a CV for the position of Senior Android Developer\u00a0\u2013 AT&T\n\u2013 An experienced Developer is needed for an excellent and dynamic team working on challenging mobile solutions.\n\u2013 The candidate will take part in mobile projects development as well as research of new solutions.\nRequirements:\n\u2013\u00a0BS.c. in computer science or other relevant degree.\n\u2013\u00a02+ years of software development experience.\n\u2013\u00a0Object oriented and SW design skills.\n\u2013\u00a02+ years of native iOS\\OSX development.\n\u2013\u00a0Strong ObjectiveC knowledge.\n\u2013\u00a0familiar with Apple products, environment, OS & Xcode.\nTo send a CV for the position of IOS Developer \u2013 HPE Software\n\u2013 An innovative and unique startup company in Haifa, with an excellent team and cutting edge technology in the wearable domain is looking for an experienced android developer.\n\u2013 The job offers an opportunity to design and create an android based system and applications with extensive connectivity, reach UI, real time processing, ROM modifications and much more using the most up-to-date state-of-the-art technologies out there.\n\u2013 Desired Skills and Experience.\nRequirements:\n\u2013 First degree in Computer Science from a known institute.\n\u2013 Android development experience.\n\u2013 Deep knowledge and extensive experience in Java, Android Studio, C and NDK.\n\u2013 At least 4 years of proven experience with Java and Android development.\n\u2013 Significant Experience in responsive UI and Layouts, graphics, animations, IPC, background services, high performance processing, multithreading and the various Android OS mechanisms and services.\n\u2013 Significant Experience in Bluetooth communication (mainly 4.0).\n\u2013 Knowledge and Experience with low level android development and ROM modifications.\n\u2013 Knowledge with 3D programming, Video streaming and image processing.\n\u2013 Experience with third-party libraries and APIs.\n\u2013 Experience in building client\u2013server applications.\n\u2013 Experience in REST and with integration with external APIs like Google Services (e.g. maps), Social networks (e.g. Facebook).\n\u2013 Advantage to developers with knowledge in: GIS, Sport platforms (e.g. Strava) and IOS development.\n\u2013 Advantage to Cyclists.\n\u2013 The developer must be a team player with the ability of self-learning.\nTo send a CV for the position of Android Developer \u2013 \u05d0\u05dc\u05d1\u05d9\u05d8 \u05de\u05e2\u05e8\u05db\u05d5\u05ea \u05d1\u05e2\u201d\u05de\n\u05de\u05e6\u05d8\u05e8\u05e4\u05d9\u05dd \u05dc\u05e6\u05d5\u05d5\u05ea \u05e6\u05e2\u05d9\u05e8, \u05de\u05d2\u05e0\u05d9\u05d1 \u05d5\u05de\u05d2\u05d5\u05d1\u05e9 \u05d1\u05d7\u05d1\u05e8\u05ea \u05d4\u05d9\u05d9\u05d8\u05e7 \u05de\u05e6\u05dc\u05d9\u05d7\u05d4 \u05d5\u05de\u05ea\u05d2\u05de\u05dc\u05ea\n\u05e2\u05d5\u05d1\u05d3\u05d9\u05dd \u05e7\u05e9\u05d4 \u05d5\u05e0\u05d4\u05e0\u05d9\u05dd \u05de\u05db\u05dc \u05e8\u05d2\u05e2!\nRequirements:\n\u2013 \u05e0\u05d9\u05e1\u05d9\u05d5\u05df \u05e9\u05dc 2 \u05dc\u05e4\u05d7\u05d5\u05ea \u05d1\u05e4\u05d9\u05ea\u05d5\u05d7 Android \u2013 \u05d7\u05d5\u05d1\u05d4!\n\u2013 \u05e0\u05d9\u05e1\u05d9\u05d5\u05df \u05d1\u05e4\u05d9\u05ea\u05d5\u05d7 Java server.\n\u2013 \u05ea\u05d5\u05d0\u05e8 \u05e8\u05dc\u05d5\u05d5\u05e0\u05d8\u05d9 \u05de\u05de\u05d5\u05e1\u05d3 \u05d0\u05e7\u05d3\u05de\u05d9 \u05d8\u05d5\u05d1 (\u05d0\u05d5\u05e0\u05d9\u05d1\u05e8\u05e1\u05d9\u05d8\u05d4 \u05d0\u05d5 \u05d8\u05db\u05e0\u05d9\u05d5\u05df) \u2013 \u05d7\u05d5\u05d1\u05d4!\n\u2013 \u05e8\u05e2\u05d1 \u05dc\u05d4\u05ea\u05e4\u05ea\u05d7 \u05d5\u05dc\u05dc\u05de\u05d5\u05d3.\n\u2013 \u05d9\u05db\u05d5\u05dc\u05ea \u05dc\u05d4\u05e9\u05ea\u05dc\u05d1 \u05d1\u05e2\u05d1\u05d5\u05d3\u05ea \u05e6\u05d5\u05d5\u05ea.\nTo send a CV for the position of log-on \u2013 \u05d3\u05e8\u05d5\u05e9/\u05d4 \u05de\u05e4\u05ea\u05d7/\u05ea Android", "keywords": "mobile web developer,general motors,\u05d2\u2019\u05e0\u05e8\u05dc \u05de\u05d5\u05d8\u05d5\u05e8\u05e1 technical leader/manager in the cloud and mobile dep.,ibm senior android developer,liveperson,ios developer,agt international,jive,c++ mobile developer,plarium,senior android developer,at&t,hpe software,android developer,\u05d0\u05dc\u05d1\u05d9\u05d8 \u05de\u05e2\u05e8\u05db\u05d5\u05ea \u05d1\u05e2\u201d\u05de,log-on,\u05d3\u05e8\u05d5\u05e9/\u05d4 \u05de\u05e4\u05ea\u05d7/\u05ea android,at&t,\u05d2\u05d9\u05e7 \u05d2\\'\u05d9\u05d1,\u05d2\u05d9\u05e7\u05d2\u05d5\\'\u05d1,\u05d3\u05e8\u05d5\u05e9\u05d9\u05dd,\u05de\u05d4\u05e0\u05d3\u05e1\u05d9\u05dd,\u05de\u05e0\u05d4\u05dc\u05d9\u05dd,\u05de\u05e9\u05e8\u05d5\u05ea,\u05de\u05e9\u05e8\u05d5\u05ea \u05d1\u05d4\u05d9\u05d9-\u05d8\u05e7"}