{"url": "https://www.geektime.co.il/hitech-jobs-26-january/", "type": "article", "title": "\u05de\u05d7\u05e4\u05e9\u05d9\u05dd \u05e2\u05d1\u05d5\u05d3\u05d4? 10 \u05de\u05e9\u05e8\u05d5\u05ea \u05d7\u05d3\u05e9\u05d5\u05ea \u05d1\u05d4\u05d9\u05d9\u05d8\u05e7", "description": "\u05e8\u05d9\u05db\u05d6\u05e0\u05d5 \u05e2\u05d1\u05d5\u05e8\u05db\u05dd 10 \u05de\u05e9\u05e8\u05d5\u05ea \u05d8\u05e8\u05d9\u05d5\u05ea \u05de\u05d4\u05dc\u05d5\u05d7\u05d5\u05ea \u05e9\u05dc\u05e0\u05d5 \u05e2\u05dd \u05db\u05dc \u05d4\u05e4\u05e8\u05d8\u05d9\u05dd \u05d4\u05e8\u05dc\u05d5\u05d5\u05e0\u05d8\u05d9\u05dd. \u05e2\u05db\u05e9\u05d9\u05d5 \u05e0\u05d5\u05ea\u05e8 \u05dc\u05db\u05dd \u05e8\u05e7 \u05dc\u05e2\u05d1\u05d5\u05e8, \u05dc\u05d1\u05d3\u05d5\u05e7 \u05d5\u05dc\u05e4\u05e0\u05d5\u05ea \u05dc\u05d0\u05dc\u05d5 \u05d4\u05e8\u05dc\u05d5\u05d5\u05e0\u05d8\u05d9\u05dd \u05e2\u05d1\u05d5\u05e8\u05db\u05dd", "image": "https://files.geektime.co.il/wp-content/uploads/2017/01/computer-1185637_1280-e1485346990773.jpg", "tag": "\u05d0\u05d9\u05e0\u05d8\u05e8\u05e0\u05d8", "publisher": "https://www.facebook.com/geektimecoil", "published_time": "2017-01-26T16:20:28Z", "modified_time": "2017-01-26T15:16:25Z", "articleBody": "\u05e8\u05d9\u05db\u05d6\u05e0\u05d5 \u05e2\u05d1\u05d5\u05e8\u05db\u05dd 10 \u05de\u05e9\u05e8\u05d5\u05ea \u05d8\u05e8\u05d9\u05d5\u05ea \u05de\u05d4\u05dc\u05d5\u05d7\u05d5\u05ea \u05e9\u05dc\u05e0\u05d5 \u05e2\u05dd \u05db\u05dc \u05d4\u05e4\u05e8\u05d8\u05d9\u05dd \u05d4\u05e8\u05dc\u05d5\u05d5\u05e0\u05d8\u05d9\u05dd. \u05e2\u05db\u05e9\u05d9\u05d5 \u05e0\u05d5\u05ea\u05e8 \u05dc\u05db\u05dd \u05e8\u05e7 \u05dc\u05e2\u05d1\u05d5\u05e8, \u05dc\u05d1\u05d3\u05d5\u05e7 \u05d5\u05dc\u05e4\u05e0\u05d5\u05ea \u05dc\u05d0\u05dc\u05d5 \u05d4\u05e8\u05dc\u05d5\u05d5\u05e0\u05d8\u05d9\u05dd \u05e2\u05d1\u05d5\u05e8\u05db\u05dd\n\u05de\u05e7\u05d5\u05e8: Pixabay\n\u05d0\u05d7\u05ea \u05d4\u05de\u05d8\u05e8\u05d5\u05ea \u05dc\u05e9\u05de\u05df \u05d9\u05d9\u05e1\u05d3\u05e0\u05d5 \u05d0\u05ea \u05d2\u05d9\u05e7\u05d8\u05d9\u05d9\u05dd \u05d4\u05d9\u05ea\u05d4 \u05dc\u05e7\u05d3\u05dd \u05d0\u05ea \u05e7\u05d4\u05d9\u05dc\u05ea \u05d4\u05d4\u05d9\u05d9\u05d8\u05e7 \u05d1\u05d0\u05e8\u05e5. \u05d1\u05e4\u05d5\u05e1\u05d8 \u05d4\u05d2\u05d9\u05e7\u05d2\u2019\u05d5\u05d1 \u05d4\u05e9\u05d1\u05d5\u05e2\u05d9, \u05d0\u05e0\u05d7\u05e0\u05d5 \u05de\u05e4\u05e8\u05e1\u05de\u05d9\u05dd \u05d7\u05dc\u05e7 \u05de\u05d4\u05de\u05e9\u05e8\u05d5\u05ea \u05d4\u05de\u05e4\u05d5\u05e8\u05e1\u05de\u05d5\u05ea \u05d1\u05dc\u05d5\u05d7 \u05de\u05e9\u05e8\u05d5\u05ea \u05d4\u05d4\u05d9\u05d9\u05d8\u05e7 \u05d4\u05d7\u05d3\u05e9 \u05e9\u05dc \u05d2\u05d9\u05e7\u05d8\u05d9\u05d9\u05dd. \u05d0\u05dd \u05d0\u05ea\u05dd \u05de\u05e2\u05d5\u05e0\u05d9\u05d9\u05e0\u05d9\u05dd \u05dc\u05de\u05e6\u05d5\u05d0 \u05de\u05e9\u05e8\u05d5\u05ea \u05e0\u05d5\u05e1\u05e4\u05d5\u05ea \u05d0\u05d5 \u05dc\u05e4\u05e8\u05e1\u05dd \u05de\u05e9\u05e8\u05d5\u05ea \u05e9\u05dc\u05db\u05dd, \u05d0\u05ea\u05dd \u05de\u05d5\u05d6\u05de\u05e0\u05d9\u05dd \u05dc\u05e2\u05e9\u05d5\u05ea \u05d6\u05d0\u05ea \u05d1\u05d0\u05de\u05e6\u05e2\u05d5\u05ea \u05dc\u05d5\u05d7 \u05d4\u05de\u05e9\u05e8\u05d5\u05ea \u05d4\u05d7\u05d3\u05e9 \u05e9\u05dc\u05e0\u05d5 \u2013 Geeklist. \u05e9\u05ea\u05e4\u05d5 \u05d0\u05ea \u05d4\u05e4\u05d5\u05e1\u05d8 \u05d5\u05d4\u05e2\u05d1\u05d9\u05e8\u05d5 \u05d4\u05dc\u05d0\u05d4 \u05db\u05d3\u05d9 \u05dc\u05e2\u05d6\u05d5\u05e8 \u05dc\u05d7\u05d1\u05e8\u05d5\u05ea \u05dc\u05d4\u05e4\u05d9\u05e5 \u05d0\u05ea \u05d4\u05de\u05e9\u05e8\u05d5\u05ea \u05d5\u05dc\u05d2\u05d5\u05dc\u05e9\u05d9 \u05d2\u05d9\u05e7\u05d8\u05d9\u05d9\u05dd \u05dc\u05de\u05e6\u05d5\u05d0 \u05d0\u05ea \u05d4\u05e2\u05d1\u05d5\u05d3\u05d4 \u05d4\u05d7\u05d3\u05e9\u05d4 \u05e9\u05d4\u05dd \u05de\u05d7\u05e4\u05e9\u05d9\u05dd.\nAs our UX/UI Designer you will work closely with multiple teams, mainly Product, R&D and Branding to ensure the creation of engaging, positive, user experiences and intuitive interfaces for both web and mobile applications.\nIn this role, you will create smart, beautiful and responsive designs for both our online solutions as well as our leading Back-office products by defining interaction models and understanding and communicating user scenarios and end-to-end experiences.\nYou will play a key role in turning big ideas into simple, beautiful features and dealing with the continuous challenge of making the complicated simple, fun and accessible while juggling between multiple types of products with different kinds of audiences.\nRequirements:\n\u2013 1-5 years of experience designing online web interfaces, either consumer or back-office/SaaS (Both preferred).\n\u2013 Very strong knowledge and solid understanding of UX/UI, Interest in the experience and feelings people go through \u2013 not just how it looks\n\u2013 Extensive experience producing high-quality, pixel perfect designs, from concept to production\n\u2013 A fast learner and a focused team player, with passion to constantly learn and acquire new tools and knowledge\n\u2013 Extensive experience in Photoshop and Illustrator\n\u2013 Vast experience in wire-framing and mock-ups, usage of tools such as Axure and Invision are a major advantage.\n\u2013 Team player with great communication skills. You should be able to clearly articulate your design decisions and what problems they\u2019re solving.\n\u2013 A Can-do Attitude.\n\u2013 Experience working in an Agile environment, participating in team Product Backlog grooming sessions to grasp the greater picture \u2013 major advantage.\n\u2013 Degree in Interactive Design/Human Interactions/Cognitive sciences/Visual Communication or a related field \u2013 Preferred.\n\u2013 Please provide a portfolio of your design work as part of the application.\nTo send a CV for the position of UI/UX \u2013 Salestech\nWe are looking for a skilled designer with strong UI and design abilitiesto interpret ideas into a design engagement. If you excel at providing both analytical as well as creative ideas into a design engagement, we would love to tell you more about this incredible opportunity!\nResponsibilities:\n\u2013 Executing interaction design and visual design as a part of a multi-disciplinary team\n\u2013 Execute all visual design stages from concept to final hand-off to programming\n\u2013 Take broad, conceptual ideas and turn them into something useful and valuable\n\u2013 Design flows and experiences that are incredibly simple and elegant\n\u2013 Work closely with the design marketing and technology teams to conceptualize and prototype interface functionality, look, and feel.\n\u2013 Design online marketing materials, products and web templates\n\u2013 Partner with PMs, programmers, engineers, researchers and content strategists to oversee the user experience of a product from conception until launch\nRequirements:\n\u2013 A strong & creative online portfolio.\n\u2013 Bachelor\u2019s or Master\u2019s degree in Graphic / Visual Communication / interaction design or related design field.\n\u2013 Passion for Online Design & Web.\n\u2013 Experience with user interface design patterns.\n\u2013 Conceptual thinking both in visual and in interactive design.\n\u2013 Excellent communication skills and strong attention to details.\n\u2013 Up to date with industry leading design software and technologies\n\u2013 Experience with HTML & CSS at designer level \u2013 an advantage.\n\u2013 Willing to work full time (not a freelance)\n\u2013 B.Sc. in Industrial Engineering / Software Engineering\nTo send a CV for the position of Product / UI Designer \u2013 Seebo\nThe Marketing Department is the fastest growing department at Plarium, and its focus is not merely to expose as many people as possible to our games, but rather to bring our games to the gamers who deserve them through leading analytics. Marketing is all about combining deep, insightful performance analysis with amazing, impactful creative ideas. Our goal is to optimize our campaigns with the most effective combination of graphics, text and reach to make sure that our games reach those unique individuals who would enjoy them the most.\nThe Online Media Manager position will work with the media sales community and clients to develop unique and strategically appropriate media approaches, including the exploration of venues. The successful candidate has a significant track record generating leads and conversions for international online CPM, CPC and CPA media campaigns. The Online Media Manager will manage and optimize all aspects of deals through established new networks, implement initiatives that enhance media productivity, create new growth opportunities and increase ROI. The Online Media Manager needs to create and maintain the constant communications with partners and motivate to provide maximum exposure and revenue.\nRequirements:\n\u2013 Fluent English \u2013 written and spoken \u2013 a must, Mother tongue \u2013 Significant advantage\n\u2013 Minimum of 1+ years as an Online Media Manager\n\u2013 Proven knowledge in RMX/Appnexus \u2013 an advantage\n\u2013 Proven knowledge in Double click Ad serving platform \u2013 an advantage\n\u2013 Proven, measurable results in developing and growing an internal affiliate channel/program\n\u2013 Demonstrated ability to initiate and grow relationships\n\u2013 Knowledge and understanding of affiliate tracking methods, tagging and sale attribution\n\u2013 Ability to take on multiple projects at the same time\n\u2013 Must possess strong knowledge of the affiliate marketing industry\n\u2013 Strong organizational, analytical, presentation and problem solving skills\n\u2013 Experience in handling of tracking tools and online technologies\n\u2013 Profound knowledge of MS-Office Products (Excel in particular)\n\u2013 Passion for online games\n\u2013 BA/BS degree \u2013 an advantage\nTo send a CV for the position of Online Media Manager \u2013 Plarium\nWe are looking for hands-on Full Stack/Web Developers to design, develop, and move web-based systems/tools/dashboards to production.\nYou will work with a team to help secure the company\u2019s position at the forefront of the video advertising industry.\nWhat you\u2019ll do:\nDesign, develop, implement and move web-based systems/tools to production.\nWork with new technologies and high system availability.\nBuild deep partnerships with business, product management and technology leaders.\nRequirements:\n\u2013 3+ years hands on JavaScript: Node.js, npm, gulp, webpack.\n\u2013 2+ years in Front End: HTML, CSS.\n\u2013 3+ years in Back End: PHP or Java, OOP.\n\u2013 Experience with SQL/NoSQL databases.\n\u2013 Experience with Angular and React \u2013 preferred.\n\u2013 Experience with Linux, AWS, Apache/Nginx/Tomcat \u2013 preferred.\n\u2013 Work in agile/scrum environment \u2013 preferred.\n\u2013 Web technologies \u2013 preferred.\n\u2013 B.Sc in mathematics / computer science or similar.\n\u2013 Experience in AdTech industry \u2013 preferred.\nTo send a CV for the position of Full stack / Web Developers \u2013 AnyClip\nWe are looking for an experienced sales directors to join our growing business development and sales team. \u00a0Preference for sales people that sold in to OTT video publishers such as CNN, ESPN, ABC, Disney, etc.\nJob description:\n\u2013 Qualify and nurture inbound leads for high/low touch opportunities\n\u2013 Create own opportunities and harvest them, with the help of the backend sales team\n\u2013 Personal responsibility for \u201chigh touch\u201d accounts\nRequirements:\n\u2013 Must have at least 5 years of sales experience executive, at least 2 years in the CDN market\n\u2013 Experience at CDN companies such as Akamai, Limelight, EdgeCast, Fastly, Cloudflare \u2013 advantage\n\u00a0Location:\n\u2013 For USA: preference for LA and NY\n\u2013 For EMEA: preference for Germany, UK, \u00a0or France\no send a CV for the position of Sales Director \u2013 Hola Better Internet\nDevelop your career, get acknowledged for your efforts, and work with dedicated people who love what they do in one of Tel Aviv\u2019s top startups\nOptimove\u2019s Customer-Success Manager (CSM) fills a dynamic and essential client-facing role, interacting collaboratively with clients, project managers and software developers to deliver outstanding results. Dedicated to our client success and satisfaction, our CSMs serve as the main point of contact with our valued customers. This role requires highly-effective management and people skills coupled with robust analytical capabilities. The CSM is a valuable member of the customer-facing team and the position is one which brings with it an excellent opportunity to learn and grow within a lively and challenging environment\nResponsibilities:\n\u2013 In charge of customer relationships\n\u2013 End-user customer training\n\u2013 Guidance and advice for enhancing the use of the system\n\u2013 Education regarding new and existing features\n\u2013 Ongoing customer enablement\nRequirements:\n\u2013 Excellent spoken and written English\n\u2013 Strong presentation skills\n\u2013 Excellent Excel skills\n\u2013 Strong analytical skills\n\u2013 Customer enablement orientation\n\u2013 Rich and effective interpersonal skills\n\u2013 Bachelor degree in Economics or Business\n\u2013 Experience in online software or technology field \u2013 a benefit\nTo send a CV for the position of Customer Success Manager \u2013 Optimove\nAmdocs OSS division is growing and looking for exceptional Automation Tester to join a cutting edge technology project aiming at providing foundations and solution to our largest customers.\nIf you want to be part of a winning team and believe you can meet the challenge your place is with us!\n\u2013 You will Create and execute, track and report automated and manual test execution mainly in selenium and/or testNG.\n\u2013 You will Analyze defects as they arise in design or execution test phase.\n\u2013 You will Design test rules and test scenarios based on documentation and communication with Product Management, Functional designers and developers.\n\u2013 You will Identify and propose work-around for critical defects.\n\u2013 You will be challenged with leading the technical aspects of the project.\n\u2013 You will have the opportunity to work in a growing business group, with ever growing opportunities for personal growth.\n\u2013 You will have the opportunity to work with the industry most advanced technologies.\n\u2013 You will work with great people who care and love their job.\nRequirements:\n\u2013 BSC in computer or industrial engineering or B.A. in any exact Science (information system proficiency an advantage).\n\u2013 At least 2 years relevant testing experience\n\u2013 Object Oriented programming \u2013 class structure, code re-use, abstract thinking.\n\u2013 Data model understanding.\n\u2013 Familiar with Client/Server applications, HTML and Java Script, Java.\n\u2013 Knowledge in SQL & DB development environment.\n\u2013 Basic Unix knowledge.\n\u2013 Experience in creating selenium/testNG scripts and adopt automation framework \u2013 an advantage.\n\u2013 Familiar with Amdocs testing methodology & tools \u2013 an advantage.\n\u2013 Ability to multi-task.\n\u2013 Very good interpersonal and communication skills.\n\u2013 Experience in working with customers and on customer sites.\n\u2013 Very good analytical skills.\n\u2013 Ability to work and learn\u00a0independently.\nTo send a CV for the position of Software Test Engineer \u2013 Amdocs\nWe are looking for extremely talented and sharp QA for interesting work in an Agile R&D Mobile team to build and execute manual (mostly) and automatic tests, as part of our Core\u00a0team.\n\u2013 You will be creating and executing test plans for mobile clients and server APIs.\n\u2013 You will be configuring remote servers and be the master of their logs.\n\u2013 If you have passion for Mobile and have a \u201cdo what it takes to win\u201d mentality we would want to see you part of our team.\nRequirements:\n\u2013 A High-School Graduate Majoring in Computer Science and Mathematics \u2013 Must\n\u2013 QA exeprince- Advantage\u200b\n\u2013 IDF technology units\u00a0\u00a0Graduate \u2013 Advantage\n\u2013 Development Scripting Experience \u2013 Advantage\n\u2013 Availability\u00a0for at least a year\nTo send a CV for the position of Manual QA \u2013 Vonage\nGigya\u2019s R&D center in Azrieli towers in Tel-Aviv is looking for a senior C# developer with strong software engineering skills, to develop high-quality, advanced infrastructures and micro-services for use by other R&D teams in the company.\nAbout the position:\nDevelop advanced infrastructures that enable other teams to develop micro-services.\nGreat interpersonal skills, supporting developers and integrating new infrastructures\nStriving to improve R&D productivity\nDevelop various micro-services.\nWork in an Agile environmet\nAt Gigya, we can promise you three things:\n\u2013 A challenging environment \u2013 You will work with the most cutting edge technologies \u00a0available contributing to your development experience and professional skillset. At Gigya, your code will reach 1.5 billion users per month.\n\u2013 Inspiration \u2013 You will work with other techies and experienced, battle-hardened managers, who will push you to new limits and help you develop your full potential. At Gigya, the best idea wins.\n\u2013 Convenient and fun \u2013 Our offices are located in Azrieli Towers with a breathtaking view and are easily accessible by bus, car and train. We\u2019ve got the best gadgets and frequently participate in fun, exciting and team-building activities.\nRequirements:\n\u2013 5+ years of experience with C#/Java/C++, minimum 2 years with C#.\n\u2013 Ability to write clean and simple code to solve complex problems using advanced software engineering techniques.\n\u2013 Real-world experience with advanced concepts such as async/await, functional programming, AOP, serialization, concurrency and scalability.\n\u2013 Developed or participated in developing at least 2 core systems.\n\u2013 Advantage: open-source contributions\nTo send a CV for the position of Senior C# Infrastructure/server developer \u2013 Gigya\nCheck point Software Technologies is looking for a junior system administrator to be responsible for:\nprovide 24\u00d77 1stlevel support to Check Point \u2018systems\u2019 and networks\nTroubleshoot ongoing problems\nreact to monitoring alerts\nprovide proactive maintenance to various systems\nwork closely with IT department personnel for escalations\nparticipating in installations and setup of Check Point infrastructure\nRequirements:\n\u2013 1-2 years of experience in Linux \u2013 Red Hat/CentOS\n\u2013 1-2 years of experience in networking (TCP/IP) and switching\n\u2013 Web systems \u2013 Apache & Tomcat \u2013 Advantage\n\u2013 Applicative data base management \u2013 Oracle, MySQL, or other \u2013 Advantage\n\u2013 VMware ESX configuration \u2013 Advantage\n\u2013 Microsoft servers experience (AD, Exchange) \u2013 Advantage\nproven troubleshooting skills\n\u2013 Self-learning\n\u2013 Good inter-personal ability and team work\n\u2013 Advantage \u2013 scripting skills: Bash, Python, Ruby, PowerShell\nPlease send CVs to email: Jobs@webpals.com including position number #2139 in the subject line.\n\u00a0\u05e8\u05d5\u05e6\u05d9\u05dd \u05dc\u05e8\u05d0\u05d5\u05ea \u05de\u05e9\u05e8\u05d5\u05ea \u05e0\u05d5\u05e1\u05e4\u05d5\u05ea? \u05db\u05e0\u05e1\u05d5 \u05e2\u05db\u05e9\u05d9\u05d5 \u05dc\u05d2\u05d9\u05e7\u05dc\u05d9\u05e1\u05d8, \u05d4\u05dc\u05d5\u05d7 \u05e9\u05dc \u05d7\u05d1\u05e8\u05d5\u05ea \u05d4\u05d4\u05d9\u05d9-\u05d8\u05e7 \u05d1\u05d9\u05e9\u05e8\u05d0\u05dc >>>", "keywords": "system & network administrator,manual qa,vonage,check point,software test engineer,amdocs,customer success manager,sales director,hola better internet,junior user acquisition,tgs,online media manager,plarium,optimove,product / ui designer,seebo,ui/ux,salestech,senior c# infrastructure/server developer,gigya,,system & network administrator,anyclip,full stack / web developers,\u200bsalestech\u200b,\u05d2\u05d9\u05e7 \u05d2\\'\u05d9\u05d1,\u05d2\u05d9\u05e7\u05d2\u05d5\\'\u05d1,\u05d3\u05e8\u05d5\u05e9\u05d9\u05dd,\u05de\u05d4\u05e0\u05d3\u05e1\u05d9\u05dd,\u05de\u05e0\u05d4\u05dc\u05d9\u05dd,\u05de\u05e4\u05ea\u05d7\u05d9\u05dd,\u05de\u05e9\u05e8\u05d5\u05ea,\u05de\u05e9\u05e8\u05d5\u05ea \u05d1\u05d4\u05d9\u05d9-\u05d8\u05e7"}